langevals_google_cloud/dlp_pii_detection.py
langevals_google_cloud-0.1.8.dist-info/METADATA
langevals_google_cloud-0.1.8.dist-info/WHEEL
langevals_google_cloud-0.1.8.dist-info/RECORD
