Metadata-Version: 2.1
Name: langevals-google-cloud
Version: 0.1.8
Summary: LangEvals integration for Google Cloud APIs evaluators
License: MIT
Author: Rogerio Chaves
Author-email: rogerio@langwatch.ai
Requires-Python: >=3.11,<4.0
Classifier: License :: OSI Approved :: MIT License
Classifier: Programming Language :: Python :: 3
Classifier: Programming Language :: Python :: 3.11
Classifier: Programming Language :: Python :: 3.12
Classifier: Programming Language :: Python :: 3.13
Requires-Dist: google-cloud-dlp (>=3.16.0,<4.0.0)
Requires-Dist: langevals-core (>=0.1.12,<0.2.0)
